pyjsonapi/__init__.py
pyjsonapi/model.py
pyjsonapi/relationship.py
pyjsonapi/session.py
pyjsonapi/utils.py
jsonapi_python-0.1.1.post2.dist-info/LICENSE
jsonapi_python-0.1.1.post2.dist-info/METADATA
jsonapi_python-0.1.1.post2.dist-info/WHEEL
jsonapi_python-0.1.1.post2.dist-info/RECORD
