Metadata-Version: 2.1
Name: jsonapi-python
Version: 0.1.1.post2
Summary: Python JSON:API implementation
Home-page: https://github.com/david-why/pyjsonapi
License: MIT
Author: david-why
Author-email: david_why@outlook.com
Requires-Python: >=3.10,<4.0
Classifier: License :: OSI Approved :: MIT License
Classifier: Programming Language :: Python :: 3
Classifier: Programming Language :: Python :: 3.10
Classifier: Programming Language :: Python :: 3.11
Classifier: Programming Language :: Python :: 3.12
Classifier: Typing :: Typed
Requires-Dist: aiohttp (>=3.9.3,<4.0.0)
Requires-Dist: pydantic (>=2.6.4,<3.0.0)
Requires-Dist: requests (>=2.31.0,<3.0.0)
Project-URL: Issues, https://github.com/david-why/pyjsonapi/issues
Project-URL: Repository, https://github.com/david-why/pyjsonapi
